{
  "events": [
    {
      "thinking": "The user's workspace is cluttered with several beverage containers (soda cans, paper cups) in close proximity to the experimental materials, including the well plate and pipette tips. This constitutes poor lab practice and increases the risk of accidental spills and contamination of the experiment.",
      "timestamp_range": "0:00 - 1:12",
      "warning_message": "Workspace Clutter and Contamination Risk",
      "description": "Drinks on bench near experiment"
    },
    {
      "thinking": "The user dispenses the first reagent, 30\u00b5l of 'A', into well A1. According to the plan, this well still needs 30\u00b5l of reagent 'B' to be complete.",
      "timestamp_range": "0:14 - 0:16",
      "well_id": "A1",
      "is_complete": false,
      "current_contents": [
        {
          "name": "A",
          "volume_ul": 30.0
        }
      ],
      "missing_reagents": [
        {
          "name": "B",
          "volume_ul": 30.0
        }
      ]
    },
    {
      "thinking": "The user dispenses the first reagent, 30\u00b5l of 'A', into well A2. According to the plan, this well still needs 30\u00b5l of reagent 'C' to be complete.",
      "timestamp_range": "0:20 - 0:22",
      "well_id": "A2",
      "is_complete": false,
      "current_contents": [
        {
          "name": "A",
          "volume_ul": 30.0
        }
      ],
      "missing_reagents": [
        {
          "name": "C",
          "volume_ul": 30.0
        }
      ]
    },
    {
      "thinking": "The user adds 30\u00b5l of reagent 'B' to well A1, which already contains 30\u00b5l of reagent 'A'. The well now contains all required reagents as per the experimental plan and is considered complete.",
      "timestamp_range": "0:37 - 0:38",
      "well_id": "A1",
      "is_complete": true,
      "current_contents": [
        {
          "name": "A",
          "volume_ul": 30.0
        },
        {
          "name": "B",
          "volume_ul": 30.0
        }
      ],
      "missing_reagents": []
    },
    {
      "thinking": "The user dispenses the first reagent, 30\u00b5l of 'B', into well A3. According to the plan, this well still needs 30\u00b5l of reagent 'C' to be complete.",
      "timestamp_range": "0:41 - 0:43",
      "well_id": "A3",
      "is_complete": false,
      "current_contents": [
        {
          "name": "B",
          "volume_ul": 30.0
        }
      ],
      "missing_reagents": [
        {
          "name": "C",
          "volume_ul": 30.0
        }
      ]
    },
    {
      "thinking": "The user adds 30\u00b5l of reagent 'C' to well A2, which already contains 30\u00b5l of reagent 'A'. The well now contains all required reagents as per the experimental plan and is considered complete.",
      "timestamp_range": "0:56 - 0:58",
      "well_id": "A2",
      "is_complete": true,
      "current_contents": [
        {
          "name": "A",
          "volume_ul": 30.0
        },
        {
          "name": "C",
          "volume_ul": 30.0
        }
      ],
      "missing_reagents": []
    },
    {
      "thinking": "The user adds 30\u00b5l of reagent 'C' to well A3, which already contains 30\u00b5l of reagent 'B'. The well now contains all required reagents as per the experimental plan and is considered complete.",
      "timestamp_range": "1:00 - 1:03",
      "well_id": "A3",
      "is_complete": true,
      "current_contents": [
        {
          "name": "B",
          "volume_ul": 30.0
        },
        {
          "name": "C",
          "volume_ul": 30.0
        }
      ],
      "missing_reagents": []
    }
  ]
}